<?xml version="1.0" encoding="utf-8"?>
<actor version="1">
  <castshadow/>
  <group>
    <variant name="celt dock rubble struct">
      <mesh>props/celt_dock_rubble_struct.dae</mesh>
      <textures>
        <texture file="structural/destroyed/celt_struct_1.png" name="baseTex"/>
        <texture file="structural/celt_struct_1_norm.png" name="normTex"/>
        <texture file="structural/celt_struct_1_spec.png" name="specTex"/>
        <texture file="props/ao/celt_dock_rubble_ao.png" name="aoTex"/>
      </textures>
    </variant>
  </group>
  <material>player_trans_ao_parallax_spec.xml</material>
</actor>
